oic/__init__.py
oic/exception.py
oic/py.typed
oic/extension/__init__.py
oic/extension/client.py
oic/extension/device_flow.py
oic/extension/heart.py
oic/extension/message.py
oic/extension/pop.py
oic/extension/popjwt.py
oic/extension/proof_of_possesion.py
oic/extension/provider.py
oic/extension/signed_http_req.py
oic/extension/single.py
oic/extension/sts.py
oic/extension/token.py
oic/oauth2/__init__.py
oic/oauth2/base.py
oic/oauth2/consumer.py
oic/oauth2/exception.py
oic/oauth2/grant.py
oic/oauth2/message.py
oic/oauth2/provider.py
oic/oauth2/util.py
oic/oic/__init__.py
oic/oic/claims_provider.py
oic/oic/consumer.py
oic/oic/message.py
oic/oic/provider.py
oic/utils/__init__.py
oic/utils/aes.py
oic/utils/authz.py
oic/utils/claims.py
oic/utils/client_management.py
oic/utils/clientdb.py
oic/utils/http_util.py
oic/utils/jwt.py
oic/utils/keyio.py
oic/utils/restrict.py
oic/utils/sanitize.py
oic/utils/sdb.py
oic/utils/session_backend.py
oic/utils/settings.py
oic/utils/shelve_wrapper.py
oic/utils/stateless.py
oic/utils/template_render.py
oic/utils/time_util.py
oic/utils/token_handler.py
oic/utils/webfinger.py
oic/utils/authn/__init__.py
oic/utils/authn/authn_context.py
oic/utils/authn/client.py
oic/utils/authn/client_saml.py
oic/utils/authn/javascript_login.py
oic/utils/authn/ldap_member.py
oic/utils/authn/ldapc.py
oic/utils/authn/multi_auth.py
oic/utils/authn/saml.py
oic/utils/authn/user.py
oic/utils/authn/user_cas.py
oic/utils/rp/__init__.py
oic/utils/rp/oauth2.py
oic/utils/userinfo/__init__.py
oic/utils/userinfo/aa_info.py
oic/utils/userinfo/distaggr.py
oic/utils/userinfo/ldap_info.py
oic-1.7.0.dist-info/LICENSE.txt
oic-1.7.0.dist-info/METADATA
oic-1.7.0.dist-info/WHEEL
oic-1.7.0.dist-info/entry_points.txt
oic-1.7.0.dist-info/top_level.txt
oic-1.7.0.dist-info/RECORD
