Metadata-Version: 2.1
Name: oic
Version: 1.7.0
Summary: Python implementation of OAuth2 and OpenID Connect
Home-page: https://github.com/CZ-NIC/pyoidc/
Author: Roland Hedberg
Author-email: roland@catalogix.se
License: Apache 2.0
Classifier: Development Status :: 4 - Beta
Classifier: License :: OSI Approved :: Apache Software License
Classifier: Programming Language :: Python :: 3.8
Classifier: Programming Language :: Python :: 3.9
Classifier: Programming Language :: Python :: 3.10
Classifier: Programming Language :: Python :: 3.11
Classifier: Topic :: Software Development :: Libraries :: Python Modules
Requires-Python: ~=3.8
License-File: LICENSE.txt
Requires-Dist: requests
Requires-Dist: pycryptodomex
Requires-Dist: pydantic-settings
Requires-Dist: pyjwkest>=1.3.6
Requires-Dist: mako
Requires-Dist: cryptography
Requires-Dist: defusedxml
Requires-Dist: typing_extensions; python_version < "3.8"
Provides-Extra: develop
Requires-Dist: cherrypy==3.2.4; extra == "develop"
Requires-Dist: pyOpenSSL; extra == "develop"
Provides-Extra: testing
Requires-Dist: responses; extra == "testing"
Requires-Dist: testfixtures; extra == "testing"
Requires-Dist: pytest; extra == "testing"
Requires-Dist: freezegun; extra == "testing"
Provides-Extra: docs
Requires-Dist: Sphinx; extra == "docs"
Requires-Dist: sphinx-autobuild; extra == "docs"
Requires-Dist: alabaster; extra == "docs"
Requires-Dist: autodoc_pydantic>=2.0.0; extra == "docs"
Provides-Extra: quality
Requires-Dist: pylama; extra == "quality"
Requires-Dist: isort; extra == "quality"
Requires-Dist: eradicate; extra == "quality"
Requires-Dist: mypy; extra == "quality"
Requires-Dist: black; extra == "quality"
Requires-Dist: bandit; extra == "quality"
Requires-Dist: readme_renderer[md]; extra == "quality"
Provides-Extra: types
Requires-Dist: types-requests; extra == "types"
Provides-Extra: ldap-authn
Requires-Dist: python-ldap; extra == "ldap-authn"
Provides-Extra: examples
Requires-Dist: beaker; extra == "examples"
